CHANGES.txt
CONTRIBUTORS.txt
LICENSE.txt
MANIFEST.in
README.txt
setup.cfg
setup.py
repoze/__init__.py
repoze.bitblt.egg-info/PKG-INFO
repoze.bitblt.egg-info/SOURCES.txt
repoze.bitblt.egg-info/dependency_links.txt
repoze.bitblt.egg-info/entry_points.txt
repoze.bitblt.egg-info/namespace_packages.txt
repoze.bitblt.egg-info/not-zip-safe
repoze.bitblt.egg-info/requires.txt
repoze.bitblt.egg-info/top_level.txt
repoze/bitblt/__init__.py
repoze/bitblt/processor.py
repoze/bitblt/tests.py
repoze/bitblt/transform.py